Metadata-Version: 1.2
Name: xpaw
Version: 0.12.0
Summary: Async web scraping framework
Home-page: https://github.com/jadbin/xpaw
Author: jadbin
Author-email: jadbin.com@hotmail.com
License: Apache 2
Platform: UNKNOWN
Classifier: License :: OSI Approved :: Apache Software License
Classifier: Intended Audience :: Developers
Classifier: Programming Language :: Python
Classifier: Programming Language :: Python :: 3
Classifier: Programming Language :: Python :: 3.5
Classifier: Programming Language :: Python :: 3.6
Classifier: Topic :: Internet :: WWW/HTTP
Classifier: Topic :: Software Development :: Libraries :: Application Frameworks
Requires-Python: >=3.5.3
